RIscVCPU/ALU_Control/alu_control.v
module alu_control(aluOp, funct7, funct3, aluControl);
    input [1:0] aluOp;
    input [6:0] funct7;
    input [2:0] funct3;
    output reg [3:0] aluControl;

    always @(aluOp | funct7 | funct3)
        case(aluOp)
            2'b00: aluControl <= 4'b0010; //add (for ld & sd instruction)
            2'b01: aluControl <= 4'b0110; //sub (for beq instruction)

            // R-type instructions
            2'b10: casex({funct7, funct3})
                    10'b0000000000: aluControl <= 4'b0010; //add
                    10'b0000000111: aluControl <= 4'b0000; //and
                    10'b0000000110: aluControl <= 4'b0001; //or
                    10'b0100000000: aluControl <= 4'b0110; //sub
                    default: aluControl <= 4'bxxxx;
                endcase

            default: aluControl <= 4'bxxxx;
        endcase
endmodule

RIscVCPU/Control/control.v
module control(opcode, branch, memRead, memToReg, aluOp, memWrite, aluSrc, regWrite);
    input[6:0] opcode;
    output branch, memRead, memToReg, memWrite, aluSrc ,regWrite;
    output [1:0] aluOp;

    reg [7:0] controls;
    assign {aluSrc, memToReg, regWrite, memRead, memWrite, branch, aluOp} = controls;

    always @(opcode)
        casex(opcode)
            7'b0110011: controls <= 8'b00100010;  // R-Type
            7'b0000011: controls <= 8'b11110000;  // ld
            7'b0100011: controls <= 8'b1x001000;  // sd
            7'b1100011: controls <= 8'b0x000101;  // beq
            default:    controls <= 8'bxxxxxxxx;  // illegal operation
        endcase
endmodule

RIscVCPU/ALU_Control/alu_control_tb.v
`timescale 1ns / 1ns
`include "../Control/control.v"
`include "alu_control.v"

module alu_control_tb;
   reg clk;
   reg [31:0] instruction;
   wire [6:0] opcode;
   wire branch, memRead, memToReg, memWrite, aluSrc , regWrite;
   wire [1:0] aluOp;
   wire [6:0] funct7;
   wire [2:0] funct3;
   wire [3:0] aluControl;

   wire [7:0] controls;  
   assign controls = {aluSrc, memToReg, regWrite, memRead, memWrite, branch, aluOp};

   assign opcode = instruction[6:0];
   assign funct3 = instruction[14:12];
   assign funct7 = instruction[31:25];  

   
   control ctrl(opcode, branch, memRead, memToReg, aluOp, memWrite, aluSrc, regWrite);
   alu_control alu_ctrl(aluOp, funct7, funct3, aluControl);
    always #5 clk <= (!clk);

   initial begin
      clk <= 0;
      $dumpfile("alu_control_tb.vcd");
      $dumpvars(0, alu_control_tb);

      @(posedge clk); instruction <= 32'h00512003; $strobe("add (ld):\t\tALUOp = %b\t\t aluControl = %b", aluOp, aluControl);

      @(posedge clk); instruction <= 32'h000122A3; $strobe("add (sd):\t\tALUOp = %b\t\t aluControl = %b", aluOp, aluControl);

      @(posedge clk); instruction <= 32'h00104263; $strobe("subtract (beq):\t\tALUOp = %b\t\t aluControl = %b", aluOp, aluControl);

      @(posedge clk); instruction <= 32'h00208033; $strobe("add (R-type):\t\tALUOp = %b\t\t aluControl = %b", aluOp, aluControl);

      @(posedge clk); instruction <= 32'h41FF8FB3; $strobe("subtract (R-type):\tALUOp = %b\t\t aluControl = %b", aluOp, aluControl);

      @(posedge clk); instruction <= 32'h0056F033; $strobe("AND (R-type):\t\tALUOp = %b\t\t aluControl = %b", aluOp, aluControl);

      @(posedge clk); instruction <= 32'h0178E1B3; $strobe("OR (R-type):\t\tALUOp = %b\t\t aluControl = %b", aluOp, aluControl);

      @(posedge clk); instruction <= 32'hFFFFFFFF; $strobe("ILLEGAL OP:\t\tALUOp = %b\t\t aluControl = %b\n", aluOp, aluControl);

      #15 $finish;
   end
endmodule

RIscVCPU/ALU_Control/alu_control_tb.vcd
$date
	Sat Dec 18 11:14:03 2021
$end
$version
	Icarus Verilog
$end
$timescale
	1ns
$end
$scope module alu_control_tb $end
$var wire 1 ! regWrite $end
$var wire 7 " opcode [6:0] $end
$var wire 1 # memWrite $end
$var wire 1 $ memToReg $end
$var wire 1 % memRead $end
$var wire 7 & funct7 [6:0] $end
$var wire 3 ' funct3 [2:0] $end
$var wire 8 ( controls [7:0] $end
$var wire 1 ) branch $end
$var wire 1 * aluSrc $end
$var wire 2 + aluOp [1:0] $end
$var wire 4 , aluControl [3:0] $end
$var reg 1 - clk $end
$var reg 32 . instruction [31:0] $end
$scope module alu_ctrl $end
$var wire 3 / funct3 [2:0] $end
$var wire 7 0 funct7 [6:0] $end
$var wire 2 1 aluOp [1:0] $end
$var reg 4 2 aluControl [3:0] $end
$upscope $end
$scope module ctrl $end
$var wire 7 3 opcode [6:0] $end
$var wire 1 ! regWrite $end
$var wire 1 # memWrite $end
$var wire 1 $ memToReg $end
$var wire 1 % memRead $end
$var wire 1 ) branch $end
$var wire 1 * aluSrc $end
$var wire 2 4 aluOp [1:0] $end
$var reg 8 5 controls [7:0] $end
$upscope $end
$upscope $end
$enddefinitions $end
#0
$dumpvars
bx 5
bx 4
bx 3
bx 2
bx 1
bx 0
bx /
bx .
0-
bx ,
bx +
x*
x)
bx (
bx '
bx &
x%
x$
x#
bx "
x!
$end
#5
b10 ,
b10 2
1*
1$
1!
1%
0#
0)
b11110000 (
b0 +
b0 1
b0 4
b11110000 5
b11 "
b11 3
b10 '
b10 /
b0 &
b0 0
b10100010010000000000011 .
1-
#10
0-
#15
x$
0!
0%
b1x001000 (
1#
b1x001000 5
b100011 "
b100011 3
b10010001010100011 .
1-
#20
0-
#25
b110 ,
b110 2
0*
0#
1)
b0x000101 (
b1 +
b1 1
b1 4
b0x000101 5
b1100011 "
b1100011 3
b100 '
b100 /
b100000100001001100011 .
1-
#30
0-
#35
b10 ,
b10 2
0$
1!
0)
b100010 (
b10 +
b10 1
b10 4
b100010 5
b110011 "
b110011 3
b0 '
b0 /
b1000001000000000110011 .
1-
#40
0-
#45
b110 ,
b110 2
b100000 &
b100000 0
b1000001111111111000111110110011 .
1-
#50
0-
#55
b0 ,
b0 2
b111 '
b111 /
b0 &
b0 0
b10101101111000000110011 .
1-
#60
0-
#65
b1 ,
b1 2
b110 '
b110 /
b1011110001110000110110011 .
1-
#70
0-
#75
x*
x$
x!
x%
x#
x)
bx (
bx +
bx 1
bx 4
bx ,
bx 2
bx 5
b1111111 "
b1111111 3
b111 '
b111 /
b1111111 &
b1111111 0
b11111111111111111111111111111111 .
1-
