RIscVCPU/Mux/mux.v
module mux (A, B, selection, out);
    parameter n = 32;
    input [n-1:0] A, B;
    input selection;
    output [n-1:0] out;

    assign out = (selection == 1) ? B : A;
endmodule

RIscVCPU/Mux/mux_tb.v
`timescale 1ns / 1ns

`include "mux.v"

module mux_tb;
    reg clk;
    reg[ 31:0] A, B;
    wire [31:0] out;
    reg selection;

    mux mux_instance (A, B, selection , out);
    always #5 clk <= (!clk);
    initial begin
      clk <= 0;
      $dumpfile("mux_tb.vcd");
      $dumpvars(0, mux_tb);

      @(posedge clk); A = 0; B = 32'h12345678; selection <= 0; display; @(posedge clk); selection <= 1; display;

      @(posedge clk); A = 0; B = 32'h87654321; selection <= 0; display; @(posedge clk); selection <= 1; display;

      @(posedge clk);  A = 32'h11112222; B=0; selection <= 0; display; @(posedge clk); selection <= 1; display;
      
      @(posedge clk);  A = 32'd122; B=0; selection <= 0;$display("A = %0d B = %0d selection = %0b out = %0d", A, B, selection, out); @(posedge clk); selection <= 1; $display("A = %0d B = %0d selection = %0b out = %0d", A, B, selection, out);

      @(posedge clk);  A = 32'b11110000; B=0; selection <= 0; $display("A = %0b B = %0b selection = %0b out = %0b", A, B, selection, out); @(posedge clk); selection <= 1; $display("A = %0b B = %0b selection = %0b out = %0b", A, B, selection, out);
      #20 $finish;
    end

    task display;
      #1 $display("A = %0h B = %0h selection = %0b out = %0h", A, B, selection, out);
    endtask
endmodule

RIscVCPU/Mux/mux_tb.vcd
$date
	Sat Dec 18 16:02:40 2021
$end
$version
	Icarus Verilog
$end
$timescale
	1ns
$end
$scope module mux_tb $end
$var wire 32 ! out [31:0] $end
$var reg 32 " A [31:0] $end
$var reg 32 # B [31:0] $end
$var reg 1 $ clk $end
$var reg 1 % selection $end
$scope module mux_instance $end
$var wire 32 & A [31:0] $end
$var wire 32 ' B [31:0] $end
$var wire 1 % selection $end
$var wire 32 ( out [31:0] $end
$upscope $end
$scope task display $end
$upscope $end
$upscope $end
$enddefinitions $end
#0
$dumpvars
bx (
bx '
bx &
x%
0$
bx #
bx "
bx !
$end
#5
0%
b0 !
b0 (
b10010001101000101011001111000 #
b10010001101000101011001111000 '
b0 "
b0 &
1$
#10
0$
#15
b10010001101000101011001111000 !
b10010001101000101011001111000 (
1%
1$
#20
0$
#25
0%
b0 !
b0 (
b10000111011001010100001100100001 #
b10000111011001010100001100100001 '
1$
#30
0$
#35
b10000111011001010100001100100001 !
b10000111011001010100001100100001 (
1%
1$
#40
0$
#45
0%
b10001000100010010001000100010 !
b10001000100010010001000100010 (
b0 #
b0 '
b10001000100010010001000100010 "
b10001000100010010001000100010 &
1$
#50
0$
#55
b0 !
b0 (
1%
1$
#60
0$
#65
b1111010 !
b1111010 (
0%
b1111010 "
b1111010 &
1$
#70
0$
#75
b0 !
b0 (
1%
1$
#80
0$
#85
b11110000 !
b11110000 (
0%
b11110000 "
b11110000 &
1$
#90
0$
#95
b0 !
b0 (
1%
1$
