RIscVCPU/Register/registers.v
module registers(regWrite, readRegister1, readRegister2, writeRegister, writeData, readData1, readData2, clk);  
    input [4:0] readRegister1, readRegister2, writeRegister;
    input [63:0] writeData;
    output reg [63:0] readData1, readData2;
    reg [63:0] registerFile [0:31];
    input clk, regWrite;

    always @(readRegister1) 
        readData1 <= (readRegister1 != 0) ? registerFile[readRegister1] : 0;

    always @(readRegister2)
        readData2 <= (readRegister2 != 0) ? registerFile[readRegister2] : 0;
    
    always @(posedge clk) 
        if (regWrite) registerFile[writeRegister] <= writeData;
endmodule

RIscVCPU/Part1riscV/Register/registers_tb.v
`timescale 1ns / 1ns

`include "registers.v"

module registers_tb;  
    reg [4:0] readRegister1, readRegister2, writeRegister;
    reg [63:0] writeData;
    wire [63:0] readData1, readData2;
    reg clk;
    reg regWrite;
    integer i;

  
    registers myregisters(regWrite, readRegister1, readRegister2, writeRegister, writeData, readData1, readData2, clk);
    // initial clk <= 0;
     always #5 clk <= (!clk);
    initial begin
        clk <= 0;
        $dumpfile("registers_tb.vcd");
        $dumpvars(0, registers_tb);

        i = 0;
        while(i <= 15) begin
            @(posedge clk); readRegister1 <= i;  readRegister2 <= i+1;
            i = i+1;
        end

        #15 regWrite <= 1; writeData = 32'h12345678;
        i = 0;
        while(i <= 15) begin
            @(posedge clk); writeRegister <= i;  writeData <= i+1;
            i = i+1;
        end
        #15 readRegister1<=32'hXXXXXXXX; readRegister2<=32'hXXXXXXXX; regWrite<=0;

        i = 0;
        while(i <= 15) begin
            @(posedge clk); readRegister1 <= i;  readRegister2 <= i+1;
            i = i+1;
        end
        #15 $finish;
    end
endmodule

RIscVCPU/Register/registers_tb.vcd
$date
	Sat Dec 04 23:15:42 2021
$end
$version
	Icarus Verilog
$end
$timescale
	1ns
$end
$scope module registers_tb $end
$var wire 64 ! readData2 [63:0] $end
$var wire 64 " readData1 [63:0] $end
$var reg 1 # clk $end
$var reg 5 $ readRegister1 [4:0] $end
$var reg 5 % readRegister2 [4:0] $end
$var reg 1 & regWrite $end
$var reg 64 ' writeData [63:0] $end
$var reg 5 ( writeRegister [4:0] $end
$var integer 32 ) i [31:0] $end
$scope module myregisters $end
$var wire 1 # clk $end
$var wire 5 * readRegister1 [4:0] $end
$var wire 5 + readRegister2 [4:0] $end
$var wire 1 & regWrite $end
$var wire 64 , writeData [63:0] $end
$var wire 5 - writeRegister [4:0] $end
$var reg 64 . readData1 [63:0] $end
$var reg 64 / readData2 [63:0] $end
$upscope $end
$upscope $end
$enddefinitions $end
#0
$dumpvars
bx /
bx .
bx -
bx ,
bx +
bx *
b0 )
bx (
bx '
x&
bx %
bx $
0#
bx "
bx !
$end
#5
b0 "
b0 .
b1 %
b1 +
b0 $
b0 *
b1 )
1#
#10
0#
#15
bx "
bx .
b10 %
b10 +
b1 $
b1 *
b10 )
1#
#20
0#
#25
b11 %
b11 +
b10 $
b10 *
b11 )
1#
#30
0#
#35
b100 %
b100 +
b11 $
b11 *
b100 )
1#
#40
0#
#45
b101 %
b101 +
b100 $
b100 *
b101 )
1#
#50
0#
#55
b110 %
b110 +
b101 $
b101 *
b110 )
1#
#60
0#
#65
b111 %
b111 +
b110 $
b110 *
b111 )
1#
#70
0#
#75
b1000 %
b1000 +
b111 $
b111 *
b1000 )
1#
#80
0#
#85
b1001 %
b1001 +
b1000 $
b1000 *
b1001 )
1#
#90
0#
#95
b1010 %
b1010 +
b1001 $
b1001 *
b1010 )
1#
#100
0#
#105
b1011 %
b1011 +
b1010 $
b1010 *
b1011 )
1#
#110
0#
#115
b1100 %
b1100 +
b1011 $
b1011 *
b1100 )
1#
#120
0#
#125
b1101 %
b1101 +
b1100 $
b1100 *
b1101 )
1#
#130
0#
#135
b1110 %
b1110 +
b1101 $
b1101 *
b1110 )
1#
#140
0#
#145
b1111 %
b1111 +
b1110 $
b1110 *
b1111 )
1#
#150
0#
#155
b10000 %
b10000 +
b1111 $
b1111 *
b10000 )
1#
#160
0#
#165
1#
#170
0#
1&
b0 )
b10010001101000101011001111000 '
b10010001101000101011001111000 ,
#175
b1 '
b1 ,
b0 (
b0 -
b1 )
1#
#180
0#
#185
b10 '
b10 ,
b1 (
b1 -
b10 )
1#
#190
0#
#195
b11 '
b11 ,
b10 (
b10 -
b11 )
1#
#200
0#
#205
b100 '
b100 ,
b11 (
b11 -
b100 )
1#
#210
0#
#215
b101 '
b101 ,
b100 (
b100 -
b101 )
1#
#220
0#
#225
b110 '
b110 ,
b101 (
b101 -
b110 )
1#
#230
0#
#235
b111 '
b111 ,
b110 (
b110 -
b111 )
1#
#240
0#
#245
b1000 '
b1000 ,
b111 (
b111 -
b1000 )
1#
#250
0#
#255
b1001 '
b1001 ,
b1000 (
b1000 -
b1001 )
1#
#260
0#
#265
b1010 '
b1010 ,
b1001 (
b1001 -
b1010 )
1#
#270
0#
#275
b1011 '
b1011 ,
b1010 (
b1010 -
b1011 )
1#
#280
0#
#285
b1100 '
b1100 ,
b1011 (
b1011 -
b1100 )
1#
#290
0#
#295
b1101 '
b1101 ,
b1100 (
b1100 -
b1101 )
1#
#300
0#
#305
b1110 '
b1110 ,
b1101 (
b1101 -
b1110 )
1#
#310
0#
#315
b1111 '
b1111 ,
b1110 (
b1110 -
b1111 )
1#
#320
0#
#325
b10000 '
b10000 ,
b1111 (
b1111 -
b10000 )
1#
#330
0#
#335
1#
#340
0#
0&
bx %
bx +
bx $
bx *
b0 )
#345
b10 !
b10 /
b0 "
b0 .
b1 %
b1 +
b0 $
b0 *
b1 )
1#
#350
0#
#355
b11 !
b11 /
b10 "
b10 .
b10 %
b10 +
b1 $
b1 *
b10 )
1#
#360
0#
#365
b100 !
b100 /
b11 "
b11 .
b11 %
b11 +
b10 $
b10 *
b11 )
1#
#370
0#
#375
b101 !
b101 /
b100 "
b100 .
b100 %
b100 +
b11 $
b11 *
b100 )
1#
#380
0#
#385
b110 !
b110 /
b101 "
b101 .
b101 %
b101 +
b100 $
b100 *
b101 )
1#
#390
0#
#395
b111 !
b111 /
b110 "
b110 .
b110 %
b110 +
b101 $
b101 *
b110 )
1#
#400
0#
#405
b1000 !
b1000 /
b111 "
b111 .
b111 %
b111 +
b110 $
b110 *
b111 )
1#
#410
0#
#415
b1001 !
b1001 /
b1000 "
b1000 .
b1000 %
b1000 +
b111 $
b111 *
b1000 )
1#
#420
0#
#425
b1010 !
b1010 /
b1001 "
b1001 .
b1001 %
b1001 +
b1000 $
b1000 *
b1001 )
1#
#430
0#
#435
b1011 !
b1011 /
b1010 "
b1010 .
b1010 %
b1010 +
b1001 $
b1001 *
b1010 )
1#
#440
0#
#445
b1100 !
b1100 /
b1011 "
b1011 .
b1011 %
b1011 +
b1010 $
b1010 *
b1011 )
1#
#450
0#
#455
b1101 !
b1101 /
b1100 "
b1100 .
b1100 %
b1100 +
b1011 $
b1011 *
b1100 )
1#
#460
0#
#465
b1110 !
b1110 /
b1101 "
b1101 .
b1101 %
b1101 +
b1100 $
b1100 *
b1101 )
1#
#470
0#
#475
b1111 !
b1111 /
b1110 "
b1110 .
b1110 %
b1110 +
b1101 $
b1101 *
b1110 )
1#
#480
0#
#485
b10000 !
b10000 /
b1111 "
b1111 .
b1111 %
b1111 +
b1110 $
b1110 *
b1111 )
1#
#490
0#
#495
bx !
bx /
b10000 "
b10000 .
b10000 %
b10000 +
b1111 $
b1111 *
b10000 )
1#
