RIscVCPU/InstructionMemory/instruction_memory.v
module instruction_memory(address, instruction);
    input [47:0] address;
    output [31:0] instruction;
    reg [31:0] RAM[0:63];

    // some random data for initialization of RAM
    initial $readmemh("instruction_memory_tb.dat", RAM);

    assign instruction = RAM[address[5:0]];
endmodule

RIscVCPU/InstructionMemory/instruction_memory_tb.v
`timescale 1ns / 1ns
`include "instruction_memory.v"

module instruction_memory_tb;
    reg clk;
    reg [47:0] address;
    wire [31:0] instruction;
    integer i;

   
    instruction_memory instruction_memory_instance (address, instruction);
    always #5 clk <= (!clk);
    initial begin
        clk <= 0;
        $dumpfile("instruction_memory_tb.vcd");
        $dumpvars(0, instruction_memory_tb);

        i = 0;
        while(i <= 15) begin
            @(posedge clk); address <= i;
            i = i+1;
        end

        #10 $finish;
    end

endmodule

RIscVCPU/InstructionMemory/instruction_memory_tb.vcd
$date
	Sat Dec 18 14:51:00 2021
$end
$version
	Icarus Verilog
$end
$timescale
	1ns
$end
$scope module instruction_memory_tb $end
$var wire 32 ! instruction [31:0] $end
$var reg 48 " address [47:0] $end
$var reg 1 # clk $end
$var integer 32 $ i [31:0] $end
$scope module instruction_memory_instance $end
$var wire 48 % address [47:0] $end
$var wire 32 & instruction [31:0] $end
$upscope $end
$upscope $end
$enddefinitions $end
#0
$dumpvars
bx &
bx %
b0 $
0#
bx "
bx !
$end
#5
b10010001101000101011001111000 !
b10010001101000101011001111000 &
b0 "
b0 %
b1 $
1#
#10
0#
#15
b10000111011001010100001100100001 !
b10000111011001010100001100100001 &
b1 "
b1 %
b10 $
1#
#20
0#
#25
b101001001100000000 !
b101001001100000000 &
b10 "
b10 %
b11 $
1#
#30
0#
#35
b101001100100000000100110010001 !
b101001100100000000100110010001 &
b11 "
b11 %
b100 $
1#
#40
0#
#45
b10010011001011000010010001000 !
b10010011001011000010010001000 &
b100 "
b100 %
b101 $
1#
#50
0#
#55
b1100100010101100100001100100001 !
b1100100010101100100001100100001 &
b101 "
b101 %
b110 $
1#
#60
0#
#65
b1010100100000010010000101000110 !
b1010100100000010010000101000110 &
b110 "
b110 %
b111 $
1#
#70
0#
#75
b100001010110000100100000110110 !
b100001010110000100100000110110 &
b111 "
b111 %
b1000 $
1#
#80
0#
#85
b1010110010001010110000101100111 !
b1010110010001010110000101100111 &
b1000 "
b1000 %
b1001 $
1#
#90
0#
#95
b101000011101111001011100100011 !
b101000011101111001011100100011 &
b1001 "
b1001 %
b1010 $
1#
#100
0#
#105
b100011010101001000011110001001 !
b100011010101001000011110001001 &
b1010 "
b1010 %
b1011 $
1#
#110
0#
#115
b10110010100010101011000010001 !
b10110010100010101011000010001 &
b1011 "
b1011 %
b1100 $
1#
#120
0#
#125
b1010000000000111000010011 !
b1010000000000111000010011 &
b1100 "
b1100 %
b1101 $
1#
#130
0#
#135
b10101010101010111100110111101111 !
b10101010101010111100110111101111 &
b1101 "
b1101 %
b1110 $
1#
#140
0#
#145
b11111111111111111111111111111111 !
b11111111111111111111111111111111 &
b1110 "
b1110 %
b1111 $
1#
#150
0#
#155
b0 !
b0 &
b1111 "
b1111 %
b10000 $
1#
