RIscVCPU/Unused_pc_stuff/Multiplexer/multiplexer_4to1.v
module multiplexer_4to1(input[3:0] W, input[1:0] S, output reg f);
    always @(W, S) begin
        case (S)
            0: f = W[0];
            1: f = W[1];
            2: f = W[2];
            3: f = W[3];
        endcase
    end
    endmodule

RIscVCPU/Unused stuffs for pc/Multiplexer/multiplexer_4to1_tb.v
`timescale 1ns / 1ns
`include "multiplexer_4to1.v"

module multiplexer_4to1_tb;
    reg [3:0] W;
    reg [1:0] S;
    wire f;
    integer i;

    multiplexer_4to1 mux (W, S, f);

    initial begin
        $dumpfile("multiplexer_4to1_tb.vcd");
        $dumpvars(0, multiplexer_4to1_tb);

        for(i = 0; i < 16; i=i+1) begin
            S = i[1:0];
            W = i;
            display;
        end
    end
    
    task display;
      #10 $display("W = %4b", W, " S = %0d", S, " f = ", f);
    endtask
endmodule

RIscVCPU/Unused_pc_stuff/Multiplexer/multiplexer_4to1_tb.vcd
$date
	Sat Dec 18 18:15:11 2021
$end
$version
	Icarus Verilog
$end
$timescale
	1ns
$end
$scope module multiplexer_4to1_tb $end
$var wire 1 ! f $end
$var reg 2 " S [1:0] $end
$var reg 4 # W [3:0] $end
$var integer 32 $ i [31:0] $end
$scope module mux $end
$var wire 2 % S [1:0] $end
$var wire 4 & W [3:0] $end
$var reg 1 ! f $end
$upscope $end
$scope task display $end
$upscope $end
$upscope $end
$enddefinitions $end
#0
$dumpvars
b0 &
b0 %
b0 $
b0 #
b0 "
0!
$end
#10
b1 #
b1 &
b1 "
b1 %
b1 $
#20
b10 #
b10 &
b10 "
b10 %
b10 $
#30
b11 #
b11 &
b11 "
b11 %
b11 $
#40
b100 #
b100 &
b0 "
b0 %
b100 $
#50
b101 #
b101 &
b1 "
b1 %
b101 $
#60
1!
b110 #
b110 &
b10 "
b10 %
b110 $
#70
0!
b111 #
b111 &
b11 "
b11 %
b111 $
#80
b1000 #
b1000 &
b0 "
b0 %
b1000 $
#90
b1001 #
b1001 &
b1 "
b1 %
b1001 $
#100
b1010 #
b1010 &
b10 "
b10 %
b1010 $
#110
1!
b1011 #
b1011 &
b11 "
b11 %
b1011 $
#120
0!
b1100 #
b1100 &
b0 "
b0 %
b1100 $
#130
b1101 #
b1101 &
b1 "
b1 %
b1101 $
#140
1!
b1110 #
b1110 &
b10 "
b10 %
b1110 $
#150
b1111 #
b1111 &
b11 "
b11 %
b1111 $
#160
b10000 $
