RIscVCPU/ALU/alu.v
module alu(X, Y, aluControl,  aluResult, zero);
    input [63:0] X, Y;
    input [3:0] aluControl;
    output reg [63:0] aluResult;
    output zero;

    assign zero = (aluResult==0) ? 1 : 0;

    always @(aluControl | X | Y)
    casex (aluControl)
        0: aluResult <= (X & Y);
        1: aluResult <= (X | Y);
        2: aluResult <= (X + Y);
        6: aluResult <= (X - Y);
        default: aluResult <= 64'bx;
    endcase
endmodule

RIscVCPU/ALU/alu_tb.v
`timescale 1ns/1ns
`include "alu.v"

module alu_tb;
    reg [63:0] X, Y; 
    reg [3:0] aluControl;
    wire [63:0] aluResult;
    wire zero;
    reg clk;
   
    alu alu_instance(X, Y, aluControl, aluResult, zero);
   always #5 clk <= (!clk);
    initial begin
        clk <= 0;
        $dumpfile("alu_tb.vcd");
        $dumpvars(0, alu_tb);

        $display("AND unit testing");
        aluControl <= 4'b0000;
        @(posedge clk); X = 64'h0000AAAA; Y = 64'h00000110; #1 $display("%4h & %4h = %4h", X, Y, aluResult);
        @(posedge clk); X = 64'hFFFFFFFF; Y = 64'h01010101; #1 $display("%4h & %4h = %4h", X, Y, aluResult);
        @(posedge clk); X = 64'b11110010; Y = 64'b01010101; #1 $display("%0b & %0b = %0b", X, Y, aluResult);
        @(posedge clk); X = 64'd6; Y = 64'd3; #1 $display("%4d & %4d = %4d", X, Y, aluResult);
        #10

        $display("\nOR unit testing");
        aluControl <= 4'b0001;
        @(posedge clk); X = 64'h0000AAAA; Y = 64'hAAAA0000; #1 $display("%4h | %4h = %4h", X, Y, aluResult);
        @(posedge clk); X = 64'h11001100; Y = 64'h01010101; #1 $display("%4h | %4h = %4h", X, Y, aluResult);
        @(posedge clk); X = 64'b11110010; Y = 64'b01010101; #1 $display("%0b | %0b = %0b", X, Y, aluResult);
        @(posedge clk); X = 64'd6; Y = 64'd3; #1 $display("%4d | %4d = %4d", X, Y, aluResult);
        #10

        $display("\nAddition unit testing");
        aluControl <= 4'b0010;
        @(posedge clk); X = 64'd123; Y = 64'd321; #1 $display("%4d + %4d = %4d", X, Y, aluResult);
        @(posedge clk); X = 64'd750; Y = 64'd250; #1 $display("%4d + %4d = %4d", X, Y, aluResult);
        @(posedge clk); X = 64'b11110010; Y = 64'b01010101; #1 $display("%0b + %0b = %0b", X, Y, aluResult);
        @(posedge clk); X = 64'd6; Y = 64'd3; #1 $display("%4d + %4d = %4d", X, Y, aluResult);
        #10

        $display("\nSubtraction unit testing");
        aluControl <= 4'b0110;
        @(posedge clk); X = 64'd128; Y = 64'd64; #1 $display("%4d - %4d = %4d", X, Y, aluResult);
        @(posedge clk); X = 64'd12345; Y = 64'd2345; #1 $display("%4d - %4d = %4d", X, Y, aluResult);
        @(posedge clk); X = 64'b11110010; Y = 64'b01010101; #1 $display("%0b - %0b = %0b", X, Y, aluResult);
        @(posedge clk); X = 64'd6; Y = 64'd3; #1 $display("%4d - %4d = %4d", X, Y, aluResult);

        #20 $finish;
    end
endmodule

RIscVCPU/ALU/alu_tb.vcd
$date
	Fri Dec 17 18:37:49 2021
$end
$version
	Icarus Verilog
$end
$timescale
	1ns
$end
$scope module alu_tb $end
$var wire 1 ! zero $end
$var wire 64 " aluResult [63:0] $end
$var reg 64 # X [63:0] $end
$var reg 64 $ Y [63:0] $end
$var reg 4 % aluControl [3:0] $end
$var reg 1 & clk $end
$scope module alu_instance $end
$var wire 64 ' X [63:0] $end
$var wire 64 ( Y [63:0] $end
$var wire 4 ) aluControl [3:0] $end
$var wire 1 ! zero $end
$var reg 64 * aluResult [63:0] $end
$upscope $end
$upscope $end
$enddefinitions $end
#0
$dumpvars
bx *
b0 )
bx (
bx '
0&
b0 %
bx $
bx #
bx "
x!
$end
#5
1!
b0 "
b0 *
b100010000 $
b100010000 (
b1010101010101010 #
b1010101010101010 '
1&
#10
0&
#15
0!
b1000000010000000100000001 "
b1000000010000000100000001 *
b1000000010000000100000001 $
b1000000010000000100000001 (
b11111111111111111111111111111111 #
b11111111111111111111111111111111 '
1&
#20
0&
#25
b1010000 "
b1010000 *
b1010101 $
b1010101 (
b11110010 #
b11110010 '
1&
#30
0&
#35
b10 "
b10 *
b11 $
b11 (
b110 #
b110 '
1&
#40
0&
#45
1&
#46
b1 %
b1 )
#50
0&
#55
b10101010101010101010101010101010 "
b10101010101010101010101010101010 *
b10101010101010100000000000000000 $
b10101010101010100000000000000000 (
b1010101010101010 #
b1010101010101010 '
1&
#60
0&
#65
b10001000000010001000100000001 "
b10001000000010001000100000001 *
b1000000010000000100000001 $
b1000000010000000100000001 (
b10001000000000001000100000000 #
b10001000000000001000100000000 '
1&
#70
0&
#75
b11110111 "
b11110111 *
b1010101 $
b1010101 (
b11110010 #
b11110010 '
1&
#80
0&
#85
b111 "
b111 *
b11 $
b11 (
b110 #
b110 '
1&
#90
0&
#95
1&
#96
b10 %
b10 )
#100
0&
#105
b110111100 "
b110111100 *
b101000001 $
b101000001 (
b1111011 #
b1111011 '
1&
#110
0&
#115
b1111101000 "
b1111101000 *
b11111010 $
b11111010 (
b1011101110 #
b1011101110 '
1&
#120
0&
#125
b101000111 "
b101000111 *
b1010101 $
b1010101 (
b11110010 #
b11110010 '
1&
#130
0&
#135
b1001 "
b1001 *
b11 $
b11 (
b110 #
b110 '
1&
#140
0&
#145
1&
#146
b110 %
b110 )
#150
0&
#155
b1000000 "
b1000000 *
b1000000 $
b1000000 (
b10000000 #
b10000000 '
1&
#160
0&
#165
b10011100010000 "
b10011100010000 *
b100100101001 $
b100100101001 (
b11000000111001 #
b11000000111001 '
1&
#170
0&
#175
b10011101 "
b10011101 *
b1010101 $
b1010101 (
b11110010 #
b11110010 '
1&
#180
0&
#185
b11 "
b11 *
b11 $
b11 (
b110 #
b110 '
1&
